{
  "account_number":"344388",
  "chain_id":"Binance-Chain-Tigris",
  "data":null,
  "memo":"test",
  "msgs":[
    {
      "inputs":[
        {
          "address":"bnb1afwh46v6nn30nkmugw5swdmsyjmlxslgjfugre",
          "coins":[
            {
              "amount":10000,
              "denom":"BNB"
            }
          ]
        }
      ],
      "outputs":[
        {
          "address":"bnb10hecgp2s4xtutcnygqny9dmpjkqkj3c07nj4kd",
          "coins":[
            {
              "amount":10000,
              "denom":"BNB"
            }
          ]
        }
      ]
    }
  ],
  "signatures":{
    "pub_key":"At3wix9RpBMsY8c0VcrGVpQEx4yeO1v/0fZOB6mi8Qm0",
    "signature":"aGKmaqijbOA9mUobpTa+ON8hE2zAjn1mGgw7sg0urcQCc3kkGbZp8nFp/oPbR1erzRRHXbNNDQDB2HEdleFdkw=="
  }
}